pyspriter.py
setup.py
pyspriter.egg-info/PKG-INFO
pyspriter.egg-info/SOURCES.txt
pyspriter.egg-info/dependency_links.txt
pyspriter.egg-info/not-zip-safe
pyspriter.egg-info/requires.txt
pyspriter.egg-info/top_level.txt