Metadata-Version: 1.0
Name: pyspriter
Version: 0.6
Summary: Command line sprite generator module for Python
Home-page: https://github.com/halilkaya/pyspriter
Author: Halil Kaya
Author-email: halil@halilkaya.net
License: MPLv2
Platform: UNKNOWN
